README.rst
_description.org
lh-agpl3-LICENSE.txt
pyproject.toml
setup.py
bisos/__init__.py
bisos.things.egg-info/PKG-INFO
bisos.things.egg-info/SOURCES.txt
bisos.things.egg-info/dependency_links.txt
bisos.things.egg-info/not-zip-safe
bisos.things.egg-info/requires.txt
bisos.things.egg-info/top_level.txt
bisos/things/__init__.py
bisos/things/toIcm.py